{
	"code": 0,
	"msg": "success",
	"count":10,
	"data": [{
			"tagId": 1,
			"tagName": "SpringBoot"
		},
		{
			"tagId": 2,
			"tagName": "SpringBoot"
		},
		{
			"tagId": 3,
			"tagName": "SpringBoot"
		},
		{
			"tagId": 4,
			"tagName": "SpringBoot"
		},
		{
			"tagId": 5,
			"tagName": "SpringBoot"
		},
		{
			"tagId": 6,
			"tagName": "SpringBoot"
		},
		{
			"tagId": 7,
			"tagName": "SpringBoot"
		},
		{
			"tagId": 8,
			"tagName": "SpringBoot"
		},
		{
			"tagId": 9,
			"tagName": "SpringBoot"
		},
		{
			"tagId": 10,
			"tagName": "SpringBoot"
		}
	]
}
